{
	"adp": {
		"timestamp": "1472422449",
		"totalDrafts": "143",
		"player": [{
			"minPick": "1",
			"maxPick": "14",
			"draftsSelectedIn": "143",
			"id": "9988",
			"averagePick": "2.03"
		}, {
			"minPick": "1",
			"maxPick": "13",
			"draftsSelectedIn": "143",
			"id": "12150",
			"averagePick": "3.62"
		}, {
			"minPick": "1",
			"maxPick": "17",
			"draftsSelectedIn": "143",
			"id": "11679",
			"averagePick": "4.48"
		}, {
			"minPick": "1",
			"maxPick": "19",
			"draftsSelectedIn": "142",
			"id": "12171",
			"averagePick": "6.31"
		}, {
			"minPick": "2",
			"maxPick": "20",
			"draftsSelectedIn": "143",
			"id": "10271",
			"averagePick": "6.36"
		}, {
			"minPick": "1",
			"maxPick": "38",
			"draftsSelectedIn": "143",
			"id": "8658",
			"averagePick": "7.71"
		}, {
			"minPick": "1",
			"maxPick": "30",
			"draftsSelectedIn": "143",
			"id": "12625",
			"averagePick": "8.77"
		}, {
			"minPick": "1",
			"maxPick": "32",
			"draftsSelectedIn": "143",
			"id": "11232",
			"averagePick": "11.04"
		}, {
			"minPick": "3",
			"maxPick": "34",
			"draftsSelectedIn": "143",
			"id": "10261",
			"averagePick": "11.77"
		}, {
			"minPick": "1",
			"maxPick": "49",
			"draftsSelectedIn": "140",
			"id": "10273",
			"averagePick": "12.79"
		}, {
			"minPick": "3",
			"maxPick": "31",
			"draftsSelectedIn": "143",
			"id": "9902",
			"averagePick": "13.24"
		}, {
			"minPick": "1",
			"maxPick": "33",
			"draftsSelectedIn": "143",
			"id": "11192",
			"averagePick": "13.30"
		}, {
			"minPick": "2",
			"maxPick": "59",
			"draftsSelectedIn": "143",
			"id": "10708",
			"averagePick": "13.78"
		}, {
			"minPick": "3",
			"maxPick": "32",
			"draftsSelectedIn": "143",
			"id": "9823",
			"averagePick": "15.19"
		}, {
			"minPick": "2",
			"maxPick": "36",
			"draftsSelectedIn": "143",
			"id": "11660",
			"averagePick": "16.31"
		}, {
			"minPick": "7",
			"maxPick": "43",
			"draftsSelectedIn": "143",
			"id": "11678",
			"averagePick": "17.15"
		}, {
			"minPick": "3",
			"maxPick": "41",
			"draftsSelectedIn": "143",
			"id": "9054",
			"averagePick": "18.46"
		}, {
			"minPick": "1",
			"maxPick": "54",
			"draftsSelectedIn": "140",
			"id": "7836",
			"averagePick": "18.83"
		}, {
			"minPick": "8",
			"maxPick": "46",
			"draftsSelectedIn": "143",
			"id": "11201",
			"averagePick": "21.71"
		}, {
			"minPick": "7",
			"maxPick": "42",
			"draftsSelectedIn": "143",
			"id": "9118",
			"averagePick": "22.45"
		}, {
			"minPick": "7",
			"maxPick": "54",
			"draftsSelectedIn": "143",
			"id": "10276",
			"averagePick": "24.43"
		}, {
			"minPick": "1",
			"maxPick": "50",
			"draftsSelectedIn": "142",
			"id": "8360",
			"averagePick": "24.48"
		}, {
			"minPick": "4",
			"maxPick": "53",
			"draftsSelectedIn": "143",
			"id": "10709",
			"averagePick": "25.32"
		}, {
			"minPick": "10",
			"maxPick": "55",
			"draftsSelectedIn": "143",
			"id": "9448",
			"averagePick": "26.64"
		}, {
			"minPick": "11",
			"maxPick": "58",
			"draftsSelectedIn": "143",
			"id": "11671",
			"averagePick": "27.01"
		}, {
			"minPick": "5",
			"maxPick": "56",
			"draftsSelectedIn": "143",
			"id": "12175",
			"averagePick": "27.08"
		}, {
			"minPick": "10",
			"maxPick": "78",
			"draftsSelectedIn": "143",
			"id": "11222",
			"averagePick": "27.70"
		}, {
			"minPick": "2",
			"maxPick": "57",
			"draftsSelectedIn": "143",
			"id": "10722",
			"averagePick": "30.17"
		}, {
			"minPick": "3",
			"maxPick": "65",
			"draftsSelectedIn": "140",
			"id": "10695",
			"averagePick": "30.52"
		}, {
			"minPick": "8",
			"maxPick": "69",
			"draftsSelectedIn": "143",
			"id": "11674",
			"averagePick": "32.36"
		}, {
			"minPick": "14",
			"maxPick": "82",
			"draftsSelectedIn": "143",
			"id": "10729",
			"averagePick": "33.77"
		}, {
			"minPick": "16",
			"maxPick": "69",
			"draftsSelectedIn": "143",
			"id": "11454",
			"averagePick": "34.13"
		}, {
			"minPick": "3",
			"maxPick": "83",
			"draftsSelectedIn": "140",
			"id": "10703",
			"averagePick": "34.78"
		}, {
			"minPick": "11",
			"maxPick": "92",
			"draftsSelectedIn": "142",
			"id": "12169",
			"averagePick": "34.94"
		}, {
			"minPick": "13",
			"maxPick": "81",
			"draftsSelectedIn": "143",
			"id": "11670",
			"averagePick": "34.96"
		}, {
			"minPick": "19",
			"maxPick": "71",
			"draftsSelectedIn": "143",
			"id": "11390",
			"averagePick": "40.00"
		}, {
			"minPick": "17",
			"maxPick": "93",
			"draftsSelectedIn": "143",
			"id": "9884",
			"averagePick": "40.15"
		}, {
			"minPick": "16",
			"maxPick": "78",
			"draftsSelectedIn": "142",
			"id": "11657",
			"averagePick": "40.15"
		}, {
			"minPick": "14",
			"maxPick": "96",
			"draftsSelectedIn": "143",
			"id": "10308",
			"averagePick": "42.73"
		}, {
			"minPick": "13",
			"maxPick": "97",
			"draftsSelectedIn": "143",
			"id": "9122",
			"averagePick": "42.85"
		}, {
			"minPick": "1",
			"maxPick": "105",
			"draftsSelectedIn": "140",
			"id": "4925",
			"averagePick": "42.95"
		}, {
			"minPick": "15",
			"maxPick": "76",
			"draftsSelectedIn": "143",
			"id": "10302",
			"averagePick": "43.48"
		}, {
			"minPick": "12",
			"maxPick": "96",
			"draftsSelectedIn": "143",
			"id": "11248",
			"averagePick": "43.48"
		}, {
			"minPick": "21",
			"maxPick": "86",
			"draftsSelectedIn": "143",
			"id": "11673",
			"averagePick": "46.74"
		}, {
			"minPick": "19",
			"maxPick": "84",
			"draftsSelectedIn": "143",
			"id": "11680",
			"averagePick": "46.94"
		}, {
			"minPick": "18",
			"maxPick": "109",
			"draftsSelectedIn": "143",
			"id": "8687",
			"averagePick": "49.50"
		}, {
			"minPick": "17",
			"maxPick": "102",
			"draftsSelectedIn": "143",
			"id": "11654",
			"averagePick": "50.62"
		}, {
			"minPick": "6",
			"maxPick": "119",
			"draftsSelectedIn": "140",
			"id": "7401",
			"averagePick": "51.04"
		}, {
			"minPick": "28",
			"maxPick": "142",
			"draftsSelectedIn": "143",
			"id": "9662",
			"averagePick": "52.22"
		}, {
			"minPick": "20",
			"maxPick": "134",
			"draftsSelectedIn": "143",
			"id": "10527",
			"averagePick": "53.92"
		}, {
			"minPick": "25",
			"maxPick": "130",
			"draftsSelectedIn": "143",
			"id": "9436",
			"averagePick": "55.41"
		}, {
			"minPick": "21",
			"maxPick": "113",
			"draftsSelectedIn": "143",
			"id": "12156",
			"averagePick": "55.64"
		}, {
			"minPick": "22",
			"maxPick": "173",
			"draftsSelectedIn": "143",
			"id": "9831",
			"averagePick": "56.17"
		}, {
			"minPick": "23",
			"maxPick": "123",
			"draftsSelectedIn": "142",
			"id": "9101",
			"averagePick": "58.91"
		}, {
			"minPick": "25",
			"maxPick": "165",
			"draftsSelectedIn": "143",
			"id": "11677",
			"averagePick": "59.17"
		}, {
			"minPick": "4",
			"maxPick": "121",
			"draftsSelectedIn": "140",
			"id": "5848",
			"averagePick": "59.66"
		}, {
			"minPick": "34",
			"maxPick": "139",
			"draftsSelectedIn": "142",
			"id": "9881",
			"averagePick": "61.78"
		}, {
			"minPick": "27",
			"maxPick": "162",
			"draftsSelectedIn": "143",
			"id": "10721",
			"averagePick": "63.62"
		}, {
			"minPick": "4",
			"maxPick": "160",
			"draftsSelectedIn": "139",
			"id": "6929",
			"averagePick": "65.21"
		}, {
			"minPick": "31",
			"maxPick": "131",
			"draftsSelectedIn": "141",
			"id": "9851",
			"averagePick": "66.21"
		}, {
			"minPick": "27",
			"maxPick": "158",
			"draftsSelectedIn": "142",
			"id": "11244",
			"averagePick": "66.80"
		}, {
			"minPick": "16",
			"maxPick": "205",
			"draftsSelectedIn": "142",
			"id": "7393",
			"averagePick": "68.78"
		}, {
			"minPick": "31",
			"maxPick": "159",
			"draftsSelectedIn": "141",
			"id": "12151",
			"averagePick": "70.16"
		}, {
			"minPick": "41",
			"maxPick": "167",
			"draftsSelectedIn": "141",
			"id": "12162",
			"averagePick": "70.69"
		}, {
			"minPick": "9",
			"maxPick": "152",
			"draftsSelectedIn": "139",
			"id": "11642",
			"averagePick": "72.35"
		}, {
			"minPick": "36",
			"maxPick": "168",
			"draftsSelectedIn": "142",
			"id": "12157",
			"averagePick": "74.13"
		}, {
			"minPick": "15",
			"maxPick": "136",
			"draftsSelectedIn": "142",
			"id": "9690",
			"averagePick": "74.62"
		}, {
			"minPick": "46",
			"maxPick": "143",
			"draftsSelectedIn": "142",
			"id": "11676",
			"averagePick": "76.65"
		}, {
			"minPick": "41",
			"maxPick": "176",
			"draftsSelectedIn": "139",
			"id": "8416",
			"averagePick": "78.34"
		}, {
			"minPick": "37",
			"maxPick": "166",
			"draftsSelectedIn": "141",
			"id": "7877",
			"averagePick": "78.55"
		}, {
			"minPick": "50",
			"maxPick": "159",
			"draftsSelectedIn": "139",
			"id": "10743",
			"averagePick": "79.91"
		}, {
			"minPick": "29",
			"maxPick": "247",
			"draftsSelectedIn": "142",
			"id": "11193",
			"averagePick": "80.06"
		}, {
			"minPick": "12",
			"maxPick": "170",
			"draftsSelectedIn": "138",
			"id": "7391",
			"averagePick": "81.33"
		}, {
			"minPick": "27",
			"maxPick": "225",
			"draftsSelectedIn": "142",
			"id": "12187",
			"averagePick": "81.61"
		}, {
			"minPick": "35",
			"maxPick": "177",
			"draftsSelectedIn": "142",
			"id": "11925",
			"averagePick": "81.80"
		}, {
			"minPick": "37",
			"maxPick": "251",
			"draftsSelectedIn": "142",
			"id": "9918",
			"averagePick": "82.99"
		}, {
			"minPick": "37",
			"maxPick": "298",
			"draftsSelectedIn": "140",
			"id": "11783",
			"averagePick": "84.49"
		}, {
			"minPick": "36",
			"maxPick": "161",
			"draftsSelectedIn": "140",
			"id": "8268",
			"averagePick": "85.16"
		}, {
			"minPick": "47",
			"maxPick": "263",
			"draftsSelectedIn": "141",
			"id": "12155",
			"averagePick": "86.78"
		}, {
			"minPick": "50",
			"maxPick": "220",
			"draftsSelectedIn": "143",
			"id": "12176",
			"averagePick": "87.12"
		}, {
			"minPick": "12",
			"maxPick": "206",
			"draftsSelectedIn": "121",
			"id": "10389",
			"averagePick": "88.40"
		}, {
			"minPick": "30",
			"maxPick": "162",
			"draftsSelectedIn": "132",
			"id": "11250",
			"averagePick": "89.45"
		}, {
			"minPick": "54",
			"maxPick": "153",
			"draftsSelectedIn": "137",
			"id": "10738",
			"averagePick": "89.80"
		}, {
			"minPick": "39",
			"maxPick": "190",
			"draftsSelectedIn": "141",
			"id": "10960",
			"averagePick": "90.38"
		}, {
			"minPick": "44",
			"maxPick": "180",
			"draftsSelectedIn": "138",
			"id": "9693",
			"averagePick": "90.62"
		}, {
			"minPick": "43",
			"maxPick": "208",
			"draftsSelectedIn": "137",
			"id": "9680",
			"averagePick": "90.66"
		}, {
			"minPick": "52",
			"maxPick": "304",
			"draftsSelectedIn": "139",
			"id": "9075",
			"averagePick": "91.18"
		}, {
			"minPick": "30",
			"maxPick": "244",
			"draftsSelectedIn": "135",
			"id": "10077",
			"averagePick": "91.30"
		}, {
			"minPick": "31",
			"maxPick": "172",
			"draftsSelectedIn": "130",
			"id": "0511",
			"averagePick": "91.48"
		}, {
			"minPick": "34",
			"maxPick": "272",
			"draftsSelectedIn": "136",
			"id": "12153",
			"averagePick": "93.16"
		}, {
			"minPick": "36",
			"maxPick": "173",
			"draftsSelectedIn": "139",
			"id": "7394",
			"averagePick": "94.47"
		}, {
			"minPick": "11",
			"maxPick": "215",
			"draftsSelectedIn": "136",
			"id": "11644",
			"averagePick": "95.71"
		}, {
			"minPick": "28",
			"maxPick": "211",
			"draftsSelectedIn": "138",
			"id": "12626",
			"averagePick": "98.49"
		}, {
			"minPick": "47",
			"maxPick": "277",
			"draftsSelectedIn": "140",
			"id": "9427",
			"averagePick": "99.18"
		}, {
			"minPick": "26",
			"maxPick": "192",
			"draftsSelectedIn": "133",
			"id": "12177",
			"averagePick": "99.22"
		}, {
			"minPick": "43",
			"maxPick": "166",
			"draftsSelectedIn": "133",
			"id": "10372",
			"averagePick": "99.43"
		}, {
			"minPick": "56",
			"maxPick": "178",
			"draftsSelectedIn": "134",
			"id": "9189",
			"averagePick": "100.01"
		}, {
			"minPick": "40",
			"maxPick": "175",
			"draftsSelectedIn": "128",
			"id": "0519",
			"averagePick": "101.84"
		}, {
			"minPick": "38",
			"maxPick": "183",
			"draftsSelectedIn": "129",
			"id": "0515",
			"averagePick": "101.92"
		}, {
			"minPick": "45",
			"maxPick": "265",
			"draftsSelectedIn": "135",
			"id": "12658",
			"averagePick": "102.12"
		}, {
			"minPick": "39",
			"maxPick": "241",
			"draftsSelectedIn": "137",
			"id": "9278",
			"averagePick": "102.66"
		}, {
			"minPick": "25",
			"maxPick": "194",
			"draftsSelectedIn": "126",
			"id": "8359",
			"averagePick": "104.83"
		}, {
			"minPick": "48",
			"maxPick": "269",
			"draftsSelectedIn": "130",
			"id": "12154",
			"averagePick": "106.42"
		}, {
			"minPick": "17",
			"maxPick": "216",
			"draftsSelectedIn": "133",
			"id": "12140",
			"averagePick": "106.78"
		}, {
			"minPick": "23",
			"maxPick": "197",
			"draftsSelectedIn": "137",
			"id": "10700",
			"averagePick": "108.23"
		}, {
			"minPick": "47",
			"maxPick": "214",
			"draftsSelectedIn": "127",
			"id": "0527",
			"averagePick": "108.77"
		}, {
			"minPick": "35",
			"maxPick": "284",
			"draftsSelectedIn": "130",
			"id": "11247",
			"averagePick": "109.06"
		}, {
			"minPick": "41",
			"maxPick": "212",
			"draftsSelectedIn": "134",
			"id": "9898",
			"averagePick": "110.97"
		}, {
			"minPick": "24",
			"maxPick": "276",
			"draftsSelectedIn": "125",
			"id": "9925",
			"averagePick": "112.80"
		}, {
			"minPick": "62",
			"maxPick": "282",
			"draftsSelectedIn": "130",
			"id": "12186",
			"averagePick": "113.48"
		}, {
			"minPick": "37",
			"maxPick": "195",
			"draftsSelectedIn": "134",
			"id": "9431",
			"averagePick": "114.37"
		}, {
			"minPick": "33",
			"maxPick": "223",
			"draftsSelectedIn": "128",
			"id": "10413",
			"averagePick": "116.12"
		}, {
			"minPick": "56",
			"maxPick": "261",
			"draftsSelectedIn": "128",
			"id": "7236",
			"averagePick": "118.53"
		}, {
			"minPick": "28",
			"maxPick": "232",
			"draftsSelectedIn": "128",
			"id": "10313",
			"averagePick": "118.77"
		}, {
			"minPick": "49",
			"maxPick": "261",
			"draftsSelectedIn": "120",
			"id": "11668",
			"averagePick": "119.09"
		}, {
			"minPick": "24",
			"maxPick": "189",
			"draftsSelectedIn": "117",
			"id": "12646",
			"averagePick": "119.22"
		}, {
			"minPick": "65",
			"maxPick": "196",
			"draftsSelectedIn": "121",
			"id": "11951",
			"averagePick": "120.04"
		}, {
			"minPick": "63",
			"maxPick": "211",
			"draftsSelectedIn": "125",
			"id": "11213",
			"averagePick": "121.55"
		}, {
			"minPick": "74",
			"maxPick": "242",
			"draftsSelectedIn": "120",
			"id": "11656",
			"averagePick": "122.16"
		}, {
			"minPick": "62",
			"maxPick": "192",
			"draftsSelectedIn": "110",
			"id": "12205",
			"averagePick": "123.37"
		}, {
			"minPick": "68",
			"maxPick": "200",
			"draftsSelectedIn": "124",
			"id": "0532",
			"averagePick": "123.69"
		}, {
			"minPick": "57",
			"maxPick": "227",
			"draftsSelectedIn": "123",
			"id": "0512",
			"averagePick": "124.74"
		}, {
			"minPick": "43",
			"maxPick": "222",
			"draftsSelectedIn": "124",
			"id": "12141",
			"averagePick": "125.55"
		}, {
			"minPick": "72",
			"maxPick": "233",
			"draftsSelectedIn": "118",
			"id": "10742",
			"averagePick": "126.68"
		}, {
			"minPick": "78",
			"maxPick": "256",
			"draftsSelectedIn": "114",
			"id": "10289",
			"averagePick": "126.99"
		}, {
			"minPick": "3",
			"maxPick": "293",
			"draftsSelectedIn": "100",
			"id": "7260",
			"averagePick": "127.29"
		}, {
			"minPick": "41",
			"maxPick": "292",
			"draftsSelectedIn": "107",
			"id": "12652",
			"averagePick": "128.52"
		}, {
			"minPick": "56",
			"maxPick": "224",
			"draftsSelectedIn": "113",
			"id": "10737",
			"averagePick": "129.34"
		}, {
			"minPick": "51",
			"maxPick": "294",
			"draftsSelectedIn": "113",
			"id": "9044",
			"averagePick": "129.42"
		}, {
			"minPick": "45",
			"maxPick": "275",
			"draftsSelectedIn": "123",
			"id": "9099",
			"averagePick": "130.24"
		}, {
			"minPick": "55",
			"maxPick": "298",
			"draftsSelectedIn": "114",
			"id": "12152",
			"averagePick": "130.41"
		}, {
			"minPick": "49",
			"maxPick": "249",
			"draftsSelectedIn": "109",
			"id": "12645",
			"averagePick": "131.47"
		}, {
			"minPick": "50",
			"maxPick": "255",
			"draftsSelectedIn": "123",
			"id": "9319",
			"averagePick": "132.63"
		}, {
			"minPick": "73",
			"maxPick": "226",
			"draftsSelectedIn": "101",
			"id": "11188",
			"averagePick": "133.03"
		}, {
			"minPick": "72",
			"maxPick": "248",
			"draftsSelectedIn": "110",
			"id": "7873",
			"averagePick": "133.18"
		}, {
			"minPick": "51",
			"maxPick": "226",
			"draftsSelectedIn": "114",
			"id": "11229",
			"averagePick": "133.26"
		}, {
			"minPick": "75",
			"maxPick": "274",
			"draftsSelectedIn": "111",
			"id": "11179",
			"averagePick": "133.72"
		}, {
			"minPick": "83",
			"maxPick": "221",
			"draftsSelectedIn": "117",
			"id": "0524",
			"averagePick": "136.70"
		}, {
			"minPick": "51",
			"maxPick": "267",
			"draftsSelectedIn": "121",
			"id": "10976",
			"averagePick": "137.19"
		}, {
			"minPick": "16",
			"maxPick": "281",
			"draftsSelectedIn": "107",
			"id": "6997",
			"averagePick": "137.40"
		}, {
			"minPick": "53",
			"maxPick": "285",
			"draftsSelectedIn": "122",
			"id": "9694",
			"averagePick": "137.84"
		}, {
			"minPick": "75",
			"maxPick": "233",
			"draftsSelectedIn": "95",
			"id": "12629",
			"averagePick": "139.03"
		}, {
			"minPick": "83",
			"maxPick": "230",
			"draftsSelectedIn": "94",
			"id": "10651",
			"averagePick": "139.67"
		}, {
			"minPick": "75",
			"maxPick": "297",
			"draftsSelectedIn": "107",
			"id": "10369",
			"averagePick": "139.87"
		}, {
			"minPick": "28",
			"maxPick": "231",
			"draftsSelectedIn": "96",
			"id": "7942",
			"averagePick": "140.28"
		}, {
			"minPick": "98",
			"maxPick": "233",
			"draftsSelectedIn": "84",
			"id": "12857",
			"averagePick": "142.42"
		}, {
			"minPick": "57",
			"maxPick": "223",
			"draftsSelectedIn": "111",
			"id": "0528",
			"averagePick": "142.52"
		}, {
			"minPick": "74",
			"maxPick": "250",
			"draftsSelectedIn": "109",
			"id": "0506",
			"averagePick": "143.54"
		}, {
			"minPick": "51",
			"maxPick": "258",
			"draftsSelectedIn": "100",
			"id": "8062",
			"averagePick": "144.16"
		}, {
			"minPick": "74",
			"maxPick": "276",
			"draftsSelectedIn": "75",
			"id": "11747",
			"averagePick": "145.45"
		}, {
			"minPick": "52",
			"maxPick": "283",
			"draftsSelectedIn": "118",
			"id": "8742",
			"averagePick": "145.84"
		}, {
			"minPick": "56",
			"maxPick": "283",
			"draftsSelectedIn": "93",
			"id": "10744",
			"averagePick": "146.81"
		}, {
			"minPick": "62",
			"maxPick": "308",
			"draftsSelectedIn": "122",
			"id": "10506",
			"averagePick": "146.82"
		}, {
			"minPick": "81",
			"maxPick": "287",
			"draftsSelectedIn": "92",
			"id": "4974",
			"averagePick": "147.12"
		}, {
			"minPick": "64",
			"maxPick": "207",
			"draftsSelectedIn": "89",
			"id": "11695",
			"averagePick": "147.21"
		}, {
			"minPick": "62",
			"maxPick": "260",
			"draftsSelectedIn": "100",
			"id": "10697",
			"averagePick": "147.31"
		}, {
			"minPick": "79",
			"maxPick": "236",
			"draftsSelectedIn": "106",
			"id": "0504",
			"averagePick": "147.50"
		}, {
			"minPick": "17",
			"maxPick": "250",
			"draftsSelectedIn": "58",
			"id": "10702",
			"averagePick": "147.84"
		}, {
			"minPick": "89",
			"maxPick": "249",
			"draftsSelectedIn": "92",
			"id": "10870",
			"averagePick": "149.17"
		}, {
			"minPick": "60",
			"maxPick": "304",
			"draftsSelectedIn": "84",
			"id": "12178",
			"averagePick": "150.15"
		}, {
			"minPick": "75",
			"maxPick": "226",
			"draftsSelectedIn": "84",
			"id": "10723",
			"averagePick": "150.36"
		}, {
			"minPick": "100",
			"maxPick": "287",
			"draftsSelectedIn": "90",
			"id": "9611",
			"averagePick": "150.86"
		}, {
			"minPick": "77",
			"maxPick": "295",
			"draftsSelectedIn": "118",
			"id": "11960",
			"averagePick": "151.36"
		}, {
			"minPick": "93",
			"maxPick": "251",
			"draftsSelectedIn": "88",
			"id": "9987",
			"averagePick": "151.53"
		}, {
			"minPick": "50",
			"maxPick": "300",
			"draftsSelectedIn": "92",
			"id": "0523",
			"averagePick": "151.79"
		}, {
			"minPick": "66",
			"maxPick": "284",
			"draftsSelectedIn": "73",
			"id": "12650",
			"averagePick": "152.16"
		}, {
			"minPick": "63",
			"maxPick": "292",
			"draftsSelectedIn": "68",
			"id": "12188",
			"averagePick": "152.88"
		}, {
			"minPick": "71",
			"maxPick": "238",
			"draftsSelectedIn": "73",
			"id": "11199",
			"averagePick": "153.25"
		}, {
			"minPick": "94",
			"maxPick": "245",
			"draftsSelectedIn": "68",
			"id": "10903",
			"averagePick": "153.37"
		}, {
			"minPick": "79",
			"maxPick": "303",
			"draftsSelectedIn": "64",
			"id": "12632",
			"averagePick": "153.69"
		}, {
			"minPick": "89",
			"maxPick": "277",
			"draftsSelectedIn": "73",
			"id": "11761",
			"averagePick": "153.97"
		}, {
			"minPick": "35",
			"maxPick": "293",
			"draftsSelectedIn": "76",
			"id": "9474",
			"averagePick": "154.34"
		}, {
			"minPick": "109",
			"maxPick": "248",
			"draftsSelectedIn": "59",
			"id": "12647",
			"averagePick": "155.49"
		}, {
			"minPick": "80",
			"maxPick": "243",
			"draftsSelectedIn": "52",
			"id": "9064",
			"averagePick": "156.37"
		}, {
			"minPick": "40",
			"maxPick": "234",
			"draftsSelectedIn": "50",
			"id": "11640",
			"averagePick": "156.78"
		}, {
			"minPick": "97",
			"maxPick": "275",
			"draftsSelectedIn": "68",
			"id": "12180",
			"averagePick": "157.81"
		}, {
			"minPick": "67",
			"maxPick": "253",
			"draftsSelectedIn": "54",
			"id": "12657",
			"averagePick": "158.31"
		}, {
			"minPick": "84",
			"maxPick": "323",
			"draftsSelectedIn": "100",
			"id": "2842",
			"averagePick": "158.88"
		}, {
			"minPick": "89",
			"maxPick": "256",
			"draftsSelectedIn": "95",
			"id": "0505",
			"averagePick": "158.94"
		}, {
			"minPick": "24",
			"maxPick": "234",
			"draftsSelectedIn": "94",
			"id": "0510",
			"averagePick": "159.11"
		}, {
			"minPick": "73",
			"maxPick": "234",
			"draftsSelectedIn": "46",
			"id": "12098",
			"averagePick": "159.54"
		}, {
			"minPick": "101",
			"maxPick": "236",
			"draftsSelectedIn": "69",
			"id": "12627",
			"averagePick": "159.54"
		}, {
			"minPick": "70",
			"maxPick": "254",
			"draftsSelectedIn": "60",
			"id": "12620",
			"averagePick": "160.20"
		}, {
			"minPick": "45",
			"maxPick": "231",
			"draftsSelectedIn": "35",
			"id": "10312",
			"averagePick": "160.49"
		}, {
			"minPick": "81",
			"maxPick": "291",
			"draftsSelectedIn": "104",
			"id": "11947",
			"averagePick": "160.83"
		}, {
			"minPick": "26",
			"maxPick": "262",
			"draftsSelectedIn": "61",
			"id": "8673",
			"averagePick": "160.89"
		}, {
			"minPick": "78",
			"maxPick": "238",
			"draftsSelectedIn": "51",
			"id": "8252",
			"averagePick": "161.75"
		}, {
			"minPick": "107",
			"maxPick": "226",
			"draftsSelectedIn": "47",
			"id": "12634",
			"averagePick": "161.79"
		}, {
			"minPick": "52",
			"maxPick": "296",
			"draftsSelectedIn": "40",
			"id": "7813",
			"averagePick": "162.10"
		}, {
			"minPick": "81",
			"maxPick": "290",
			"draftsSelectedIn": "98",
			"id": "11936",
			"averagePick": "162.46"
		}, {
			"minPick": "38",
			"maxPick": "261",
			"draftsSelectedIn": "41",
			"id": "10080",
			"averagePick": "162.78"
		}, {
			"minPick": "102",
			"maxPick": "221",
			"draftsSelectedIn": "47",
			"id": "12631",
			"averagePick": "162.79"
		}, {
			"minPick": "74",
			"maxPick": "322",
			"draftsSelectedIn": "101",
			"id": "10872",
			"averagePick": "163.92"
		}, {
			"minPick": "76",
			"maxPick": "309",
			"draftsSelectedIn": "45",
			"id": "12648",
			"averagePick": "164.78"
		}, {
			"minPick": "58",
			"maxPick": "288",
			"draftsSelectedIn": "60",
			"id": "10696",
			"averagePick": "165.47"
		}, {
			"minPick": "59",
			"maxPick": "299",
			"draftsSelectedIn": "39",
			"id": "12159",
			"averagePick": "165.49"
		}, {
			"minPick": "70",
			"maxPick": "212",
			"draftsSelectedIn": "57",
			"id": "10983",
			"averagePick": "165.68"
		}, {
			"minPick": "79",
			"maxPick": "240",
			"draftsSelectedIn": "31",
			"id": "11675",
			"averagePick": "166.42"
		}, {
			"minPick": "117",
			"maxPick": "219",
			"draftsSelectedIn": "12",
			"id": "8144",
			"averagePick": "166.83"
		}, {
			"minPick": "85",
			"maxPick": "281",
			"draftsSelectedIn": "74",
			"id": "0518",
			"averagePick": "167.01"
		}, {
			"minPick": "90",
			"maxPick": "306",
			"draftsSelectedIn": "56",
			"id": "11697",
			"averagePick": "167.04"
		}, {
			"minPick": "109",
			"maxPick": "238",
			"draftsSelectedIn": "52",
			"id": "9078",
			"averagePick": "167.44"
		}, {
			"minPick": "40",
			"maxPick": "248",
			"draftsSelectedIn": "38",
			"id": "9087",
			"averagePick": "167.50"
		}, {
			"minPick": "63",
			"maxPick": "289",
			"draftsSelectedIn": "65",
			"id": "10409",
			"averagePick": "167.71"
		}, {
			"minPick": "103",
			"maxPick": "236",
			"draftsSelectedIn": "49",
			"id": "12210",
			"averagePick": "167.80"
		}, {
			"minPick": "101",
			"maxPick": "231",
			"draftsSelectedIn": "36",
			"id": "11211",
			"averagePick": "168.08"
		}, {
			"minPick": "128",
			"maxPick": "208",
			"draftsSelectedIn": "9",
			"id": "0529",
			"averagePick": "168.33"
		}, {
			"minPick": "69",
			"maxPick": "257",
			"draftsSelectedIn": "77",
			"id": "0513",
			"averagePick": "168.52"
		}, {
			"minPick": "100",
			"maxPick": "268",
			"draftsSelectedIn": "65",
			"id": "0501",
			"averagePick": "169.09"
		}, {
			"minPick": "71",
			"maxPick": "288",
			"draftsSelectedIn": "16",
			"id": "10812",
			"averagePick": "169.44"
		}, {
			"minPick": "131",
			"maxPick": "222",
			"draftsSelectedIn": "14",
			"id": "11387",
			"averagePick": "169.64"
		}, {
			"minPick": "91",
			"maxPick": "306",
			"draftsSelectedIn": "25",
			"id": "12160",
			"averagePick": "169.96"
		}, {
			"minPick": "77",
			"maxPick": "245",
			"draftsSelectedIn": "14",
			"id": "9817",
			"averagePick": "170.36"
		}, {
			"minPick": "97",
			"maxPick": "218",
			"draftsSelectedIn": "31",
			"id": "12181",
			"averagePick": "170.42"
		}, {
			"minPick": "99",
			"maxPick": "238",
			"draftsSelectedIn": "58",
			"id": "12721",
			"averagePick": "171.16"
		}, {
			"minPick": "71",
			"maxPick": "287",
			"draftsSelectedIn": "27",
			"id": "11785",
			"averagePick": "171.33"
		}, {
			"minPick": "104",
			"maxPick": "266",
			"draftsSelectedIn": "31",
			"id": "10500",
			"averagePick": "171.61"
		}, {
			"minPick": "73",
			"maxPick": "299",
			"draftsSelectedIn": "39",
			"id": "10303",
			"averagePick": "171.69"
		}, {
			"minPick": "101",
			"maxPick": "328",
			"draftsSelectedIn": "63",
			"id": "11945",
			"averagePick": "172.40"
		}, {
			"minPick": "123",
			"maxPick": "292",
			"draftsSelectedIn": "50",
			"id": "7150",
			"averagePick": "172.54"
		}, {
			"minPick": "90",
			"maxPick": "270",
			"draftsSelectedIn": "40",
			"id": "6982",
			"averagePick": "172.82"
		}, {
			"minPick": "82",
			"maxPick": "286",
			"draftsSelectedIn": "8",
			"id": "10725",
			"averagePick": "173.00"
		}, {
			"minPick": "103",
			"maxPick": "234",
			"draftsSelectedIn": "46",
			"id": "9525",
			"averagePick": "173.09"
		}, {
			"minPick": "124",
			"maxPick": "228",
			"draftsSelectedIn": "27",
			"id": "12197",
			"averagePick": "173.15"
		}, {
			"minPick": "94",
			"maxPick": "325",
			"draftsSelectedIn": "69",
			"id": "5666",
			"averagePick": "173.64"
		}, {
			"minPick": "86",
			"maxPick": "244",
			"draftsSelectedIn": "46",
			"id": "9250",
			"averagePick": "173.78"
		}, {
			"minPick": "115",
			"maxPick": "276",
			"draftsSelectedIn": "35",
			"id": "0502",
			"averagePick": "174.03"
		}, {
			"minPick": "151",
			"maxPick": "209",
			"draftsSelectedIn": "15",
			"id": "12676",
			"averagePick": "174.67"
		}, {
			"minPick": "118",
			"maxPick": "221",
			"draftsSelectedIn": "25",
			"id": "11689",
			"averagePick": "174.72"
		}, {
			"minPick": "10",
			"maxPick": "306",
			"draftsSelectedIn": "9",
			"id": "11180",
			"averagePick": "175.56"
		}, {
			"minPick": "137",
			"maxPick": "210",
			"draftsSelectedIn": "16",
			"id": "8851",
			"averagePick": "175.81"
		}, {
			"minPick": "121",
			"maxPick": "264",
			"draftsSelectedIn": "45",
			"id": "8930",
			"averagePick": "176.58"
		}, {
			"minPick": "97",
			"maxPick": "244",
			"draftsSelectedIn": "24",
			"id": "11257",
			"averagePick": "176.83"
		}, {
			"minPick": "65",
			"maxPick": "284",
			"draftsSelectedIn": "20",
			"id": "7422",
			"averagePick": "177.30"
		}, {
			"minPick": "117",
			"maxPick": "269",
			"draftsSelectedIn": "36",
			"id": "0531",
			"averagePick": "177.58"
		}, {
			"minPick": "139",
			"maxPick": "208",
			"draftsSelectedIn": "10",
			"id": "10868",
			"averagePick": "177.80"
		}, {
			"minPick": "110",
			"maxPick": "282",
			"draftsSelectedIn": "35",
			"id": "9196",
			"averagePick": "178.06"
		}, {
			"minPick": "85",
			"maxPick": "215",
			"draftsSelectedIn": "10",
			"id": "10714",
			"averagePick": "178.10"
		}, {
			"minPick": "92",
			"maxPick": "288",
			"draftsSelectedIn": "62",
			"id": "0509",
			"averagePick": "179.73"
		}, {
			"minPick": "52",
			"maxPick": "323",
			"draftsSelectedIn": "9",
			"id": "11682",
			"averagePick": "179.78"
		}, {
			"minPick": "110",
			"maxPick": "222",
			"draftsSelectedIn": "20",
			"id": "12636",
			"averagePick": "180.05"
		}, {
			"minPick": "97",
			"maxPick": "272",
			"draftsSelectedIn": "22",
			"id": "12532",
			"averagePick": "180.18"
		}, {
			"minPick": "114",
			"maxPick": "326",
			"draftsSelectedIn": "45",
			"id": "8153",
			"averagePick": "180.53"
		}, {
			"minPick": "112",
			"maxPick": "290",
			"draftsSelectedIn": "43",
			"id": "0517",
			"averagePick": "180.63"
		}, {
			"minPick": "129",
			"maxPick": "312",
			"draftsSelectedIn": "37",
			"id": "10352",
			"averagePick": "181.54"
		}, {
			"minPick": "145",
			"maxPick": "268",
			"draftsSelectedIn": "23",
			"id": "12611",
			"averagePick": "181.87"
		}, {
			"minPick": "28",
			"maxPick": "287",
			"draftsSelectedIn": "14",
			"id": "0530",
			"averagePick": "182.14"
		}, {
			"minPick": "122",
			"maxPick": "281",
			"draftsSelectedIn": "19",
			"id": "0522",
			"averagePick": "182.53"
		}, {
			"minPick": "125",
			"maxPick": "282",
			"draftsSelectedIn": "33",
			"id": "7859",
			"averagePick": "182.76"
		}, {
			"minPick": "162",
			"maxPick": "207",
			"draftsSelectedIn": "8",
			"id": "12437",
			"averagePick": "183.00"
		}, {
			"minPick": "113",
			"maxPick": "292",
			"draftsSelectedIn": "21",
			"id": "11227",
			"averagePick": "183.24"
		}, {
			"minPick": "123",
			"maxPick": "277",
			"draftsSelectedIn": "21",
			"id": "0516",
			"averagePick": "183.43"
		}, {
			"minPick": "120",
			"maxPick": "271",
			"draftsSelectedIn": "28",
			"id": "9307",
			"averagePick": "183.71"
		}, {
			"minPick": "64",
			"maxPick": "268",
			"draftsSelectedIn": "13",
			"id": "0521",
			"averagePick": "183.77"
		}, {
			"minPick": "132",
			"maxPick": "303",
			"draftsSelectedIn": "22",
			"id": "11746",
			"averagePick": "184.00"
		}, {
			"minPick": "109",
			"maxPick": "238",
			"draftsSelectedIn": "12",
			"id": "12643",
			"averagePick": "184.17"
		}, {
			"minPick": "110",
			"maxPick": "297",
			"draftsSelectedIn": "38",
			"id": "0503",
			"averagePick": "184.71"
		}, {
			"minPick": "127",
			"maxPick": "274",
			"draftsSelectedIn": "20",
			"id": "12161",
			"averagePick": "184.75"
		}, {
			"minPick": "108",
			"maxPick": "269",
			"draftsSelectedIn": "22",
			"id": "11186",
			"averagePick": "185.32"
		}, {
			"minPick": "120",
			"maxPick": "237",
			"draftsSelectedIn": "12",
			"id": "12651",
			"averagePick": "185.42"
		}, {
			"minPick": "53",
			"maxPick": "310",
			"draftsSelectedIn": "12",
			"id": "11834",
			"averagePick": "186.00"
		}, {
			"minPick": "102",
			"maxPick": "279",
			"draftsSelectedIn": "30",
			"id": "0520",
			"averagePick": "186.17"
		}, {
			"minPick": "143",
			"maxPick": "262",
			"draftsSelectedIn": "15",
			"id": "10720",
			"averagePick": "188.60"
		}, {
			"minPick": "47",
			"maxPick": "284",
			"draftsSelectedIn": "31",
			"id": "9299",
			"averagePick": "188.81"
		}, {
			"minPick": "155",
			"maxPick": "319",
			"draftsSelectedIn": "15",
			"id": "12417",
			"averagePick": "189.13"
		}, {
			"minPick": "139",
			"maxPick": "296",
			"draftsSelectedIn": "37",
			"id": "6789",
			"averagePick": "189.76"
		}, {
			"minPick": "112",
			"maxPick": "219",
			"draftsSelectedIn": "10",
			"id": "12612",
			"averagePick": "190.90"
		}, {
			"minPick": "107",
			"maxPick": "277",
			"draftsSelectedIn": "15",
			"id": "10432",
			"averagePick": "191.20"
		}, {
			"minPick": "122",
			"maxPick": "299",
			"draftsSelectedIn": "11",
			"id": "11177",
			"averagePick": "192.27"
		}, {
			"minPick": "137",
			"maxPick": "278",
			"draftsSelectedIn": "18",
			"id": "3494",
			"averagePick": "193.78"
		}, {
			"minPick": "133",
			"maxPick": "294",
			"draftsSelectedIn": "20",
			"id": "0525",
			"averagePick": "193.90"
		}, {
			"minPick": "129",
			"maxPick": "294",
			"draftsSelectedIn": "18",
			"id": "10689",
			"averagePick": "195.78"
		}, {
			"minPick": "131",
			"maxPick": "265",
			"draftsSelectedIn": "9",
			"id": "12635",
			"averagePick": "196.22"
		}, {
			"minPick": "127",
			"maxPick": "282",
			"draftsSelectedIn": "10",
			"id": "11175",
			"averagePick": "196.90"
		}, {
			"minPick": "137",
			"maxPick": "237",
			"draftsSelectedIn": "12",
			"id": "12640",
			"averagePick": "196.92"
		}, {
			"minPick": "168",
			"maxPick": "235",
			"draftsSelectedIn": "10",
			"id": "12655",
			"averagePick": "197.80"
		}, {
			"minPick": "127",
			"maxPick": "310",
			"draftsSelectedIn": "24",
			"id": "9822",
			"averagePick": "201.75"
		}, {
			"minPick": "117",
			"maxPick": "256",
			"draftsSelectedIn": "16",
			"id": "11760",
			"averagePick": "202.06"
		}, {
			"minPick": "160",
			"maxPick": "296",
			"draftsSelectedIn": "15",
			"id": "8243",
			"averagePick": "202.80"
		}, {
			"minPick": "164",
			"maxPick": "298",
			"draftsSelectedIn": "11",
			"id": "11432",
			"averagePick": "203.09"
		}, {
			"minPick": "139",
			"maxPick": "289",
			"draftsSelectedIn": "12",
			"id": "9308",
			"averagePick": "203.75"
		}, {
			"minPick": "148",
			"maxPick": "237",
			"draftsSelectedIn": "8",
			"id": "12669",
			"averagePick": "204.88"
		}, {
			"minPick": "166",
			"maxPick": "317",
			"draftsSelectedIn": "10",
			"id": "12610",
			"averagePick": "208.50"
		}, {
			"minPick": "87",
			"maxPick": "295",
			"draftsSelectedIn": "11",
			"id": "9467",
			"averagePick": "208.64"
		}, {
			"minPick": "113",
			"maxPick": "293",
			"draftsSelectedIn": "9",
			"id": "11228",
			"averagePick": "215.11"
		}, {
			"minPick": "169",
			"maxPick": "318",
			"draftsSelectedIn": "10",
			"id": "12381",
			"averagePick": "216.20"
		}, {
			"minPick": "179",
			"maxPick": "272",
			"draftsSelectedIn": "8",
			"id": "12678",
			"averagePick": "217.25"
		}, {
			"minPick": "153",
			"maxPick": "302",
			"draftsSelectedIn": "10",
			"id": "12264",
			"averagePick": "218.50"
		}, {
			"minPick": "178",
			"maxPick": "275",
			"draftsSelectedIn": "11",
			"id": "11076",
			"averagePick": "219.00"
		}, {
			"minPick": "148",
			"maxPick": "293",
			"draftsSelectedIn": "9",
			"id": "9843",
			"averagePick": "219.33"
		}, {
			"minPick": "131",
			"maxPick": "300",
			"draftsSelectedIn": "10",
			"id": "12110",
			"averagePick": "231.60"
		}]
	},
	"version": "1.0",
	"encoding": "utf-8"
}